odoo/addons/pos_hide_cost_price_and_margin/README.rst
odoo/addons/pos_hide_cost_price_and_margin/__init__.py
odoo/addons/pos_hide_cost_price_and_margin/__manifest__.py
odoo/addons/pos_hide_cost_price_and_margin/i18n/it.po
odoo/addons/pos_hide_cost_price_and_margin/i18n/pos_hide_cost_price_and_margin.pot
odoo/addons/pos_hide_cost_price_and_margin/models/__init__.py
odoo/addons/pos_hide_cost_price_and_margin/models/pos_config.py
odoo/addons/pos_hide_cost_price_and_margin/models/res_config_settings.py
odoo/addons/pos_hide_cost_price_and_margin/readme/CONTRIBUTORS.md
odoo/addons/pos_hide_cost_price_and_margin/readme/CREDITS.md
odoo/addons/pos_hide_cost_price_and_margin/readme/DESCRIPTION.md
odoo/addons/pos_hide_cost_price_and_margin/readme/HISTORY.md
odoo/addons/pos_hide_cost_price_and_margin/readme/USAGE.md
odoo/addons/pos_hide_cost_price_and_margin/static/description/icon.png
odoo/addons/pos_hide_cost_price_and_margin/static/description/index.html
odoo/addons/pos_hide_cost_price_and_margin/static/src/js/product_info_popup.esm.js
odoo/addons/pos_hide_cost_price_and_margin/views/res_config_settings_views.xml
odoo_addon_pos_hide_cost_price_and_margin-17.0.1.0.0.4.dist-info/METADATA
odoo_addon_pos_hide_cost_price_and_margin-17.0.1.0.0.4.dist-info/WHEEL
odoo_addon_pos_hide_cost_price_and_margin-17.0.1.0.0.4.dist-info/top_level.txt
odoo_addon_pos_hide_cost_price_and_margin-17.0.1.0.0.4.dist-info/RECORD
