Metadata-Version: 2.1
Name: odoo-addon-pos_hide_cost_price_and_margin
Version: 17.0.1.0.0.4
Requires-Python: >=3.10
Requires-Dist: odoo>=17.0a,<17.1dev
Summary: Hide Cost and Margin on PoS
Home-page: https://github.com/OCA/pos
License: AGPL-3
Author: CampToCamp, Odoo Community Association (OCA)
Author-email: support@odoo-community.org
Classifier: Programming Language :: Python
Classifier: Framework :: Odoo
Classifier: Framework :: Odoo :: 17.0
Classifier: License :: OSI Approved :: GNU Affero General Public License v3
